objectnat/__init__.py
objectnat/_api.py
objectnat/_config.py
objectnat/_version.py
objectnat/methods/__init__.py
objectnat/methods/coverage_zones/__init__.py
objectnat/methods/coverage_zones/graph_coverage.py
objectnat/methods/coverage_zones/radius_voronoi_coverage.py
objectnat/methods/coverage_zones/stepped_coverage.py
objectnat/methods/isochrones/__init__.py
objectnat/methods/isochrones/isochrone_utils.py
objectnat/methods/isochrones/isochrones.py
objectnat/methods/noise/__init__.py
objectnat/methods/noise/noise_init_data.py
objectnat/methods/noise/noise_reduce.py
objectnat/methods/noise/noise_simulation.py
objectnat/methods/noise/noise_simulation_simplified.py
objectnat/methods/point_clustering/__init__.py
objectnat/methods/point_clustering/cluster_points_in_polygons.py
objectnat/methods/provision/__init__.py
objectnat/methods/provision/provision.py
objectnat/methods/provision/provision_exceptions.py
objectnat/methods/provision/provision_model.py
objectnat/methods/utils/__init__.py
objectnat/methods/utils/geom_utils.py
objectnat/methods/utils/graph_utils.py
objectnat/methods/utils/math_utils.py
objectnat/methods/visibility/__init__.py
objectnat/methods/visibility/visibility_analysis.py
objectnat-1.3.2.dist-info/LICENSE.txt
objectnat-1.3.2.dist-info/METADATA
objectnat-1.3.2.dist-info/WHEEL
objectnat-1.3.2.dist-info/RECORD
