Metadata-Version: 2.3
Name: ObjectNat
Version: 1.3.2
Summary: ObjectNat is an open-source library created for geospatial analysis created by IDU team
License: BSD-3-Clause
Author: DDonnyy
Author-email: 63115678+DDonnyy@users.noreply.github.com
Requires-Python: >=3.11,<3.13
Classifier: License :: OSI Approved :: BSD License
Classifier: Programming Language :: Python :: 3
Classifier: Programming Language :: Python :: 3.11
Classifier: Programming Language :: Python :: 3.12
Requires-Dist: geopandas (>=1.0.1,<2.0.0)
Requires-Dist: loguru (>=0.7.3,<0.8.0)
Requires-Dist: networkx (>=3.4.2,<4.0.0)
Requires-Dist: numpy (>=2.1.3,<3.0.0)
Requires-Dist: pandas (>=2.2.0,<3.0.0)
Requires-Dist: scikit-learn (>=1.4.0,<2.0.0)
Requires-Dist: tqdm (>=4.66.2,<5.0.0)
